oraclecloud/__init__.py
oraclecloud/iot.py
oraclecloud/storage.py
oraclecloud-0.2.dist-info/METADATA
oraclecloud-0.2.dist-info/RECORD
oraclecloud-0.2.dist-info/WHEEL
oraclecloud-0.2.dist-info/top_level.txt
