Metadata-Version: 2.1
Name: oraclecloud
Version: 0.2
Summary: Library for Oracle Public Cloud solutions
Home-page: https://github.com/waslleysouza/oraclecloud
Author: Waslley Souza
Author-email: waslleys@gmail.com
License: MIT
Platform: UNKNOWN
Classifier: Development Status :: 3 - Alpha
Classifier: License :: OSI Approved :: MIT License
Classifier: Intended Audience :: Developers
Classifier: Programming Language :: Python :: 2.7
Classifier: Programming Language :: Python :: 3
Classifier: Topic :: Software Development
Requires-Dist: numpy
Requires-Dist: pycrypto
Requires-Dist: requests
